RectangleCollision
